lccserver/__init__.py
lccserver/_version.py
lccserver/cli.py
lccserver/modtemplate.py
lccserver/utils.py
lccserver/authnzerver/__init__.py
lccserver/authnzerver/authdb.py
lccserver/authnzerver/cache.py
lccserver/authnzerver/handlers.py
lccserver/authnzerver/main.py
lccserver/authnzerver/tables.py
lccserver/authnzerver/actions/__init__.py
lccserver/authnzerver/actions/admin.py
lccserver/authnzerver/actions/apikey.py
lccserver/authnzerver/actions/email.py
lccserver/authnzerver/actions/session.py
lccserver/authnzerver/actions/user.py
lccserver/backend/__init__.py
lccserver/backend/abcat.py
lccserver/backend/abcat_columns.py
lccserver/backend/datasets.py
lccserver/backend/dbsearch.py
lccserver/backend/footprints.py
lccserver/backend/frames.py
lccserver/backend/lightcurves.py
lccserver/backend/mosaic.py
lccserver/backend/lcformat-jsons/hat-k2lc.json
lccserver/backend/lcformat-jsons/hat-sql.json
lccserver/backend/lcformat-jsons/lcformat-description.json
lccserver/external/__init__.py
lccserver/external/cookies/__init__.py
lccserver/external/cookies/cookies.py
lccserver/external/futures37/__init__.py
lccserver/external/futures37/_base.py
lccserver/external/futures37/process.py
lccserver/external/futures37/thread.py
lccserver/frontend/__init__.py
lccserver/frontend/admin_handlers.py
lccserver/frontend/auth_handlers.py
lccserver/frontend/basehandler.py
lccserver/frontend/dataserver_handlers.py
lccserver/frontend/indexserver.py
lccserver/frontend/indexserver_handlers.py
lccserver/frontend/objectserver_handlers.py
lccserver/frontend/searchserver_handlers.py
lccserver/frontend/testserver.py
lccserver/frontend/static/.DS_Store
lccserver/frontend/static/css/animate.min.css
lccserver/frontend/static/css/bootstrap.min.css
lccserver/frontend/static/css/bootstrap.min.css.map
lccserver/frontend/static/css/codehilite.css
lccserver/frontend/static/css/codemirror.css
lccserver/frontend/static/css/lcc-server.css
lccserver/frontend/static/images/favicon.png
lccserver-0.2.7.dist-info/LICENSE
lccserver-0.2.7.dist-info/METADATA
lccserver-0.2.7.dist-info/WHEEL
lccserver-0.2.7.dist-info/entry_points.txt
lccserver-0.2.7.dist-info/top_level.txt
lccserver-0.2.7.dist-info/RECORD
