Metadata-Version: 2.1
Name: lccserver
Version: 0.2.7
Summary: A light curve collection server framework.
Home-page: https://github.com/waqasbhatti/lcc-server
Author: Waqas Bhatti
Author-email: waqas.afzal.bhatti@gmail.com
License: MIT
Keywords: astronomy
Platform: UNKNOWN
Classifier: Development Status :: 4 - Beta
Classifier: License :: OSI Approved :: MIT License
Classifier: Intended Audience :: Science/Research
Classifier: Topic :: Scientific/Engineering :: Astronomy
Classifier: Operating System :: OS Independent
Classifier: Programming Language :: Python :: 3 :: Only
Classifier: Programming Language :: Python :: 3
Classifier: Programming Language :: Python :: 3.6
Classifier: Programming Language :: Python :: 3.7
Requires-Python: >=3.6
Requires-Dist: ipython (>=7.3)
Requires-Dist: numpy (>=1.16)
Requires-Dist: scipy (==1.2.1)
Requires-Dist: tornado (>=5.1)
Requires-Dist: requests (>=2.19.1)
Requires-Dist: tqdm (==4.31.1)
Requires-Dist: Markdown (==3.0.1)
Requires-Dist: pygments (==2.3.1)
Requires-Dist: cryptography (>=2.3)
Requires-Dist: astrobase (>=0.4.0)
Requires-Dist: SQLAlchemy (>=1.2.11)
Requires-Dist: passlib (==1.7.1)
Requires-Dist: bcrypt (==3.1.6)
Requires-Dist: argon2-cffi (==19.1.0)
Requires-Dist: diskcache (==3.1.1)
Requires-Dist: fuzzywuzzy (==0.17.0)
Requires-Dist: bleach (==3.1.0)
Requires-Dist: sqlparse (==0.3.0)
Requires-Dist: matplotlib (>=2.0)
Requires-Dist: shapely (>=1.6)
Requires-Dist: astropy (>=3.0)
Requires-Dist: scour (>=0.37)
Provides-Extra: postgres
Requires-Dist: psycopg2 ; extra == 'postgres'
